{
  "policy": {
    "requireUpstreamChecksum": true,
    "allowDownloadAndHash": false
  },
  "tools": [
    {
      "name": "yq",
      "repo": "mikefarah/yq",
      "version": "v4.53.2",
      "asset": "yq_linux_amd64",
      "checksumAsset": "checksums",
      "checksumFormat": "yq-checksums",
      "sha256": "d56bf5c6819e8e696340c312bd70f849dc1678a7cda9c2ad63eebd906371d56b"
    },
    {
      "name": "actionlint",
      "repo": "rhysd/actionlint",
      "version": "v1.7.12",
      "asset": "actionlint_1.7.12_linux_amd64.tar.gz",
      "checksumAsset": "actionlint_1.7.12_checksums.txt",
      "checksumFormat": "sha256sum",
      "sha256": "8aca8db96f1b94770f1b0d72b6dddcb1ebb8123cb3712530b08cc387b349a3d8"
    },
    {
      "name": "marksman",
      "repo": "artempyanykh/marksman",
      "version": "2026-02-08",
      "asset": "marksman-linux-x64",
      "checksumAsset": null,
      "checksumFormat": "github-asset-digest",
      "sha256": "be5098e8213219269c47fc0d916a66fa31ce0602ec967475c722260aabf26087"
    },
    {
      "name": "hadolint",
      "repo": "hadolint/hadolint",
      "version": "v2.14.0",
      "asset": "hadolint-linux-x86_64",
      "checksumAsset": "hadolint-linux-x86_64.sha256",
      "checksumFormat": "sha256sum",
      "sha256": "6bf226944684f56c84dd014e8b979d27425c0148f61b3bd99bcc6f39e9dc5a47"
    },
    {
      "name": "ruff",
      "repo": "astral-sh/ruff",
      "version": "0.15.12",
      "asset": "ruff-x86_64-unknown-linux-gnu.tar.gz",
      "checksumAsset": "ruff-x86_64-unknown-linux-gnu.tar.gz.sha256",
      "checksumFormat": "sha256sum",
      "sha256": "5e26a7811f7db364864ace00cced53003556a37b63f3c987e340b18207776f1c"
    }
  ]
}
